pyclipper/_pyclipper.cpython-37m-darwin.so
pyclipper/_version.py
pyclipper/__init__.py
pyclipper-1.3.0.post6.dist-info/RECORD
pyclipper-1.3.0.post6.dist-info/LICENSE
pyclipper-1.3.0.post6.dist-info/WHEEL
pyclipper-1.3.0.post6.dist-info/top_level.txt
pyclipper-1.3.0.post6.dist-info/METADATA
