Metadata-Version: 2.1
Name: pyclipper
Version: 1.3.0.post6
Summary: Cython wrapper for the C++ translation of the Angus Johnson's Clipper library (ver. 6.4.2)
Home-page: https://github.com/greginvm/pyclipper
Author: Angus Johnson, Maxime Chalton, Lukas Treyer, Gregor Ratajc
Author-email: me@gregorratajc.com
Maintainer: Cosimo Lupo
Maintainer-email: cosimo@anthrotype.com
License: MIT
Keywords: polygon clipping, polygon intersection, polygon union, polygon offsetting, polygon boolean, polygon, clipping, clipper, vatti
Platform: UNKNOWN
Classifier: Programming Language :: Python
Classifier: Programming Language :: Python :: 3
Classifier: Programming Language :: Cython
Classifier: Programming Language :: C++
Classifier: Environment :: Other Environment
Classifier: Development Status :: 4 - Beta
Classifier: Intended Audience :: Developers
Classifier: Operating System :: OS Independent
Classifier: License :: OSI Approved
Classifier: License :: OSI Approved :: MIT License
Classifier: Topic :: Multimedia :: Graphics
Classifier: Topic :: Scientific/Engineering :: Mathematics
Classifier: Topic :: Software Development :: Libraries :: Python Modules
License-File: LICENSE
